surfplot/__init__.py
surfplot/datasets.py
surfplot/plotting.py
surfplot/surf.py
surfplot/utils.py
surfplot/data/lh_default_mode_example.tsv
surfplot/data/lh_frontoparietal_example.tsv
surfplot/data/medwall.tsv
surfplot/data/rh_default_mode_example.tsv
surfplot/data/rh_frontoparietal_example.tsv
surfplot-0.2.0.dist-info/LICENSE
surfplot-0.2.0.dist-info/METADATA
surfplot-0.2.0.dist-info/WHEEL
surfplot-0.2.0.dist-info/top_level.txt
surfplot-0.2.0.dist-info/RECORD
