Metadata-Version: 2.1
Name: surfplot
Version: 0.2.0
Summary: A package for publication-ready brain surface figures
Home-page: https://surfplot.readthedocs.io/en/latest/
Author: Dan Gale
Maintainer-email: d.gale@queensu.ca
License: BSD-3
Classifier: Development Status :: 3 - Alpha
Classifier: Programming Language :: Python :: 3
Classifier: Operating System :: OS Independent
Classifier: Intended Audience :: Science/Research
Classifier: Intended Audience :: Developers
Classifier: Topic :: Scientific/Engineering
Requires-Python: >=3.7.0
Provides-Extra: test
License-File: LICENSE
